brick_cinderclient_ext/__init__.py
brick_cinderclient_ext/brick_utils.py
brick_cinderclient_ext/client.py
brick_cinderclient_ext/exceptions.py
brick_cinderclient_ext/version.py
brick_cinderclient_ext/volume_actions.py
brick_cinderclient_ext/tests/__init__.py
brick_cinderclient_ext/tests/functional/__init__.py
brick_cinderclient_ext/tests/functional/test_brick_client.py
brick_cinderclient_ext/tests/unit/__init__.py
brick_cinderclient_ext/tests/unit/test_brick_client.py
brick_cinderclient_ext/tests/unit/test_brick_utils.py
brick_cinderclient_ext/tests/unit/test_cli.py
brick_cinderclient_ext/tests/unit/test_volume_actions.py
python_brick_cinderclient_ext-2.6.0.dist-info/AUTHORS
python_brick_cinderclient_ext-2.6.0.dist-info/LICENSE
python_brick_cinderclient_ext-2.6.0.dist-info/METADATA
python_brick_cinderclient_ext-2.6.0.dist-info/WHEEL
python_brick_cinderclient_ext-2.6.0.dist-info/pbr.json
python_brick_cinderclient_ext-2.6.0.dist-info/top_level.txt
python_brick_cinderclient_ext-2.6.0.dist-info/RECORD
