Metadata-Version: 2.1
Name: python-brick-cinderclient-ext
Version: 2.6.0
Summary: python-cinderclient extension for local storage management
Home-page: http://docs.openstack.org/cinder/latest/
Author: OpenStack
Author-email: openstack-discuss@lists.openstack.org
Classifier: Environment :: OpenStack
Classifier: Intended Audience :: Information Technology
Classifier: Intended Audience :: System Administrators
Classifier: License :: OSI Approved :: Apache Software License
Classifier: Operating System :: POSIX :: Linux
Classifier: Programming Language :: Python
Classifier: Programming Language :: Python :: 3 :: Only
Classifier: Programming Language :: Python :: Implementation :: CPython
Classifier: Programming Language :: Python :: 3
Classifier: Programming Language :: Python :: 3.9
Classifier: Programming Language :: Python :: 3.10
Classifier: Programming Language :: Python :: 3.11
Classifier: Programming Language :: Python :: 3.12
Requires-Python: >=3.9
License-File: LICENSE
License-File: AUTHORS
Requires-Dist: pbr >=5.5.1
Requires-Dist: python-cinderclient >=9.0.0
Requires-Dist: os-brick >=6.0.0
Requires-Dist: oslo.concurrency >=5.0.0
Requires-Dist: netifaces >=0.11.0
